llama_index/py.typed
llama_index/vector_stores/vespa/__init__.py
llama_index/vector_stores/vespa/base.py
llama_index/vector_stores/vespa/templates.py
llama_index_vector_stores_vespa-0.3.1.dist-info/METADATA
llama_index_vector_stores_vespa-0.3.1.dist-info/WHEEL
llama_index_vector_stores_vespa-0.3.1.dist-info/licenses/LICENSE
llama_index_vector_stores_vespa-0.3.1.dist-info/RECORD
