Metadata-Version: 2.4
Name: llama-index-vector-stores-vespa
Version: 0.3.1
Summary: llama-index vector_stores vespa integration
Author-email: Thomas Thoresen <thomas@vespa.ai>
License-Expression: MIT
License-File: LICENSE
Requires-Python: <4.0,>=3.9
Requires-Dist: llama-index-core<0.15,>=0.13.0
Requires-Dist: pyvespa<0.41,>=0.40.0
